nr_metadata/__init__.py
nr_metadata/common/__init__.py
nr_metadata/common/cli.py
nr_metadata/common/config.py
nr_metadata/common/ext.py
nr_metadata/common/proxies.py
nr_metadata/common/version.py
nr_metadata/common/views.py
nr_metadata/common/alembic/__init__.py
nr_metadata/common/models/__init__.py
nr_metadata/common/models/model.json
nr_metadata/common/models/ui.json
nr_metadata/common/records/__init__.py
nr_metadata/common/records/api.py
nr_metadata/common/records/dumper.py
nr_metadata/common/records/models.py
nr_metadata/common/records/jsonschemas/__init__.py
nr_metadata/common/records/jsonschemas/common-1.0.0.json
nr_metadata/common/records/mappings/__init__.py
nr_metadata/common/records/mappings/os-v2/__init__.py
nr_metadata/common/records/mappings/os-v2/common/__init__.py
nr_metadata/common/records/mappings/os-v2/common/common-1.0.0.json
nr_metadata/common/resources/__init__.py
nr_metadata/common/resources/records/__init__.py
nr_metadata/common/resources/records/config.py
nr_metadata/common/resources/records/resource.py
nr_metadata/common/resources/records/ui.py
nr_metadata/common/services/__init__.py
nr_metadata/common/services/records/__init__.py
nr_metadata/common/services/records/config.py
nr_metadata/common/services/records/facets.py
nr_metadata/common/services/records/permissions.py
nr_metadata/common/services/records/schema.py
nr_metadata/common/services/records/search.py
nr_metadata/common/services/records/service.py
nr_metadata/common/services/records/ui_schema.py
nr_metadata/theses/__init__.py
nr_metadata/theses/cli.py
nr_metadata/theses/config.py
nr_metadata/theses/ext.py
nr_metadata/theses/proxies.py
nr_metadata/theses/version.py
nr_metadata/theses/views.py
nr_metadata/theses/alembic/__init__.py
nr_metadata/theses/models/__init__.py
nr_metadata/theses/models/model.json
nr_metadata/theses/models/ui.json
nr_metadata/theses/records/__init__.py
nr_metadata/theses/records/api.py
nr_metadata/theses/records/dumper.py
nr_metadata/theses/records/models.py
mr_metadata-1.0.0.dist-info/METADATA
mr_metadata-1.0.0.dist-info/WHEEL
mr_metadata-1.0.0.dist-info/entry_points.txt
mr_metadata-1.0.0.dist-info/top_level.txt
mr_metadata-1.0.0.dist-info/RECORD
