Metadata-Version: 2.1
Name: mr-metadata
Version: 1.0.0
Summary: "Generated metadata files for the Czech National Repository"
Home-page: https://github.com/Narodni-repozitar/ne-metadata
Author: Miroslav Simek
Author-email: simek.miroslav@techlib.cz
License: MIT
Keywords: invenio Czech NR
Platform: any
Classifier: Development Status :: 3 - Alpha
Requires-Python: >=3.9
Requires-Dist: oarepo-vocabularies (>=1.0.4)
Requires-Dist: invenio-access (>=1.4.4)
Requires-Dist: invenio-app (>=1.3.4)
Requires-Dist: invenio-db (>=1.0.14)
Requires-Dist: invenio-pidstore (>=1.2.3)
Requires-Dist: invenio-records (>=2.0.0)
Requires-Dist: invenio-records-rest (>=2.1.0)
Requires-Dist: invenio-records-permissions (>=0.13.0)
Requires-Dist: invenio-records-resources (>=0.21.4)
Requires-Dist: invenio-search (>=2.1.0)
Requires-Dist: tqdm (>=4.64.1)
Requires-Dist: oarepo-runtime (>=1.0.0)
Requires-Dist: invenio-vocabularies (>=1.0.4)
Provides-Extra: tests
Requires-Dist: pytest ; extra == 'tests'
